{
  "89seele": 284,
  "Black Nucleus": 2,
  "Celestial Hymn": 2,
  "Flame Sakitama": 2,
  "Kriegsmesser": 4,
  "Luna Kindred": 1,
  "Phoenix": 2,
  "Ritual Imayoh": 4,
  "Shadow Knight": 2,
  "Sixth Serenade": 1,
  "Valkyrie Accipiter": 1,
  "ae": 15,
  "agentrita": 593,
  "aka": 10,
  "aponia": 72,
  "asuka": 56,
  "badum": 690,
  "bk": 26,
  "bw": 41,
  "carole": 22,
  "ce": 63,
  "chenxue": 24,
  "cn": 26,
  "coralie": 134,
  "da": 46,
  "danzai": 11,
  "dj": 15,
  "dk": 12,
  "dreamseeker": 12,
  "durandal": 339,
  "eden": 30,
  "fischl": 26,
  "fov": 173,
  "fr": 21,
  "ft": 48,
  "ha": 406,
  "hare": 33,
  "hb": 42,
  "helia": 67,
  "hofi": 319,
  "hoh": 892,
  "hoo": 120,
  "hor": 42,
  "horb": 542,
  "hos": 177,
  "hot": 110,
  "hotf": 12,
  "hotr": 73,
  "hov": 17,
  "jd": 254,
  "kira": 37,
  "lantern": 176,
  "lp": 524,
  "lv": 367,
  "mobius": 80,
  "mol": 1602,
  "mpe": 186,
  "newmei": 862,
  "newseele": 1,
  "ns": 1,
  "nyx": 79,
  "pardo": 48,
  "paws": 633,
  "pe": 58,
  "pi": 13,
  "prom": 29,
  "ps": 353,
  "raven": 33,
  "roza": 22,
  "sa": 16,
  "scoralie": 548,
  "sena": 220,
  "sera": 9,
  "si": 26,
  "simp": 169,
  "sirin": 138,
  "sj": 3,
  "sn": 48,
  "songque": 13,
  "sp": 32,
  "spa": 36,
  "sparkle": 536,
  "striker": 23,
  "sushang": 28,
  "sw": 354,
  "thelema": 366,
  "theresa": 19,
  "tp": 9,
  "ur": 1,
  "vg": 17,
  "vk": 42,
  "void-drifter": 16,
  "vq": 50,
  "vv": 53,
  "youyun": 105
}